{
  "components": [
    {
      "dataType": "PL.1",
      "minOccurs": "0",
      "maxOccurs": "1"
    },
    {
      "dataType": "PL.2",
      "minOccurs": "0",
      "maxOccurs": "1"
    },
    {
      "dataType": "PL.3",
      "minOccurs": "0",
      "maxOccurs": "1"
    },
    {
      "dataType": "PL.4",
      "minOccurs": "0",
      "maxOccurs": "1"
    },
    {
      "dataType": "PL.5",
      "minOccurs": "0",
      "maxOccurs": "1"
    },
    {
      "dataType": "PL.6",
      "minOccurs": "0",
      "maxOccurs": "1"
    },
    {
      "dataType": "PL.7",
      "minOccurs": "0",
      "maxOccurs": "1"
    },
    {
      "dataType": "PL.8",
      "minOccurs": "0",
      "maxOccurs": "1"
    },
    {
      "dataType": "PL.9",
      "minOccurs": "0",
      "maxOccurs": "1"
    },
    {
      "dataType": "PL.10",
      "minOccurs": "0",
      "maxOccurs": "1"
    },
    {
      "dataType": "PL.11",
      "minOccurs": "0",
      "maxOccurs": "1"
    }
  ]
}